fastapi_depends/__init__.py
fastapi_depends/core.py
fastapi_depends/dep_container.py
fastapi_depends/fake_request.py
fastapi_depends/simple.py
fastapi_depends-0.2.1.dist-info/LICENSE
fastapi_depends-0.2.1.dist-info/WHEEL
fastapi_depends-0.2.1.dist-info/METADATA
fastapi_depends-0.2.1.dist-info/RECORD
